{
    "key": "layout_67f7c4dbb1961",
    "name": "text_image",
    "label": "Text Image",
    "display": "block",
    "sub_fields": [
        {
            "key": "field_67f7c4eed0b23",
            "label": "Title",
            "name": "title",
            "aria-label": "",
            "type": "text",
            "instructions": "",
            "required": 0,
            "conditional_logic": 0,
            "wrapper": {
                "width": "",
                "class": "",
                "id": ""
            },
            "relevanssi_exclude": 0,
            "default_value": "",
            "maxlength": "",
            "allow_in_bindings": 0,
            "placeholder": "",
            "prepend": "",
            "append": ""
        }
    ],
    "min": "",
    "max": "",
    "group": "group_588574a592c85"
}